{
  "id": null,
  "title": "VMware VSAN Monitor 66",
  "originalTitle": "VMware VSAN Monitor 66",
  "tags": [
    "VSAN",
    "HDD",
    "SSD",
    "VSAN66"
  ],
  "style": "dark",
  "timezone": "browser",
  "editable": true,
  "hideControls": false,
  "sharedCrosshair": true,
  "rows": [
    {
      "collapse": false,
      "editable": true,
      "height": "200px",
      "panels": [
        {
          "aliasColors": {},
          "bars": false,
          "datasource": null,
          "editable": true,
          "error": false,
          "fill": 1,
          "grid": {
            "leftLogBase": 1,
            "leftMax": null,
            "leftMin": 0,
            "rightLogBase": 1,
            "rightMax": null,
            "rightMin": 0,
            "threshold1": 20000,
            "threshold1Color": "rgba(216, 200, 27, 0.15)",
            "threshold2": 30000,
            "threshold2Color": "rgba(234, 112, 112, 0.22)",
            "thresholdLine": false
          },
          "id": 2,
          "legend": {
            "avg": false,
            "current": false,
            "max": false,
            "min": false,
            "show": false,
            "total": false,
            "values": false
          },
          "lines": true,
          "linewidth": 2,
          "links": [],
          "nullPointMode": "null",
          "percentage": false,
          "pointradius": 5,
          "points": false,
          "renderer": "flot",
          "scopedVars": {
            "hostname": {
              "text": "ESX",
              "value": "",
              "selected": false
            }
          },
          "seriesOverrides": [],
          "span": 2,
          "stack": false,
          "steppedLine": false,
          "targets": [
            {
              "hide": true,
              "target": "derivative(vsan.$vcenter.$datacentre.$cluster.esx.$hostname.vsan.$layer.stats.readCount)",
              "textEditor": false
            },
            {
              "hide": true,
              "target": "derivative(vsan.$vcenter.$datacentre.$cluster.esx.$hostname.vsan.$layer.stats.writeCount)",
              "textEditor": false
            },
            {
              "hide": true,
              "target": "derivative(vsan.$vcenter.$datacentre.$cluster.esx.$hostname.vsan.$layer.stats.recoveryWriteCount)",
              "textEditor": false
            },
            {
              "hide": true,
              "target": "derivative(removeBelowValue(vsan.$vcenter.$datacentre.$cluster.esx.$hostname.vsan.$layer.stats.resyncReadCount, 0))",
              "textEditor": false
            },
            {
              "target": "alias(divideSeries(derivative(vsan.$vcenter.$datacentre.$cluster.esx.$hostname.vsan.$layer.stats.readLatencySumUs), #A), 'read')",
              "textEditor": false
            },
            {
              "target": "alias(divideSeries(derivative(vsan.$vcenter.$datacentre.$cluster.esx.$hostname.vsan.$layer.stats.writeLatencySumUs), #B), 'write')",
              "textEditor": false
            },
            {
              "target": "alias(transformNull(divideSeries(derivative(vsan.$vcenter.$datacentre.$cluster.esx.$hostname.vsan.$layer.stats.recoveryWriteLatencySumUs), #C), 0), 'recoveryWrite')",
              "textEditor": false
            },
            {
              "target": "alias(transformNull(divideSeries(derivative(removeAboveValue(vsan.$vcenter.$datacentre.$cluster.esx.$hostname.vsan.$layer.stats.resyncReadLatencySumUs, 0)), #D), 0), 'resyncRead')",
              "textEditor": false
            }
          ],
          "timeFrom": null,
          "timeShift": null,
          "title": "Latencies",
          "tooltip": {
            "shared": true,
            "sort": 0,
            "value_type": "cumulative"
          },
          "transparent": false,
          "type": "graph",
          "x-axis": true,
          "y-axis": true,
          "y_formats": [
            "µs",
            "µs"
          ]
        },
        {
          "aliasColors": {
            "reads": "#6ED0E0",
            "recoveryWrites": "#EF843C",
            "resyncReadCount": "#F2C96D",
            "writes": "#E24D42"
          },
          "bars": false,
          "datasource": null,
          "editable": true,
          "error": false,
          "fill": 1,
          "grid": {
            "leftLogBase": 1,
            "leftMax": null,
            "leftMin": 0,
            "rightLogBase": 1,
            "rightMax": null,
            "rightMin": null,
            "threshold1": null,
            "threshold1Color": "rgba(216, 200, 27, 0.27)",
            "threshold2": null,
            "threshold2Color": "rgba(234, 112, 112, 0.22)"
          },
          "id": 1,
          "legend": {
            "avg": false,
            "current": false,
            "max": false,
            "min": false,
            "show": false,
            "total": false,
            "values": false
          },
          "lines": true,
          "linewidth": 2,
          "links": [],
          "nullPointMode": "null",
          "percentage": false,
          "pointradius": 5,
          "points": false,
          "renderer": "flot",
          "scopedVars": {
            "hostname": {
              "text": "ESX",
              "value": "",
              "selected": false
            }
          },
          "seriesOverrides": [],
          "span": 2,
          "stack": false,
          "steppedLine": false,
          "targets": [
            {
              "hide": false,
              "target": "alias(scaleToSeconds(derivative(vsan.$vcenter.$datacentre.$cluster.esx.$hostname.vsan.$layer.stats.readCount), 1), 'reads')",
              "textEditor": false
            },
            {
              "hide": false,
              "target": "alias(scaleToSeconds(derivative(vsan.$vcenter.$datacentre.$cluster.esx.$hostname.vsan.$layer.stats.writeCount), 1), 'writes')",
              "textEditor": false
            },
            {
              "hide": false,
              "target": "alias(scaleToSeconds(derivative(vsan.$vcenter.$datacentre.$cluster.esx.$hostname.vsan.$layer.stats.recoveryWriteCount), 1), 'recoveryWrites')",
              "textEditor": false
            },
            {
              "hide": false,
              "target": "alias(scaleToSeconds(derivative(removeBelowValue(vsan.$vcenter.$datacentre.$cluster.esx.$hostname.vsan.$layer.stats.resyncReadCount, 0)), 1), 'resyncReadCount')",
              "textEditor": false
            }
          ],
          "timeFrom": null,
          "timeShift": null,
          "title": "IOPS",
          "tooltip": {
            "shared": true,
            "sort": 0,
            "value_type": "cumulative"
          },
          "transparent": false,
          "type": "graph",
          "x-axis": true,
          "y-axis": true,
          "y_formats": [
            "short",
            "short"
          ]
        },
        {
          "aliasColors": {
            "reads": "#0A50A1",
            "recoveryWrites": "#E0752D",
            "resyncReadBytes": "#EAB839",
            "writes": "#BF1B00"
          },
          "bars": false,
          "datasource": null,
          "editable": true,
          "error": false,
          "fill": 1,
          "grid": {
            "leftLogBase": 1,
            "leftMax": null,
            "leftMin": 0,
            "rightLogBase": 1,
            "rightMax": null,
            "rightMin": null,
            "threshold1": null,
            "threshold1Color": "rgba(216, 200, 27, 0.27)",
            "threshold2": null,
            "threshold2Color": "rgba(234, 112, 112, 0.22)"
          },
          "id": 17,
          "legend": {
            "avg": false,
            "current": false,
            "max": false,
            "min": false,
            "show": false,
            "total": false,
            "values": false
          },
          "lines": true,
          "linewidth": 2,
          "links": [],
          "nullPointMode": "null",
          "percentage": false,
          "pointradius": 5,
          "points": false,
          "renderer": "flot",
          "scopedVars": {
            "hostname": {
              "text": "ESX",
              "value": "",
              "selected": false
            }
          },
          "seriesOverrides": [],
          "span": 2,
          "stack": false,
          "steppedLine": false,
          "targets": [
            {
              "target": "alias(scaleToSeconds(derivative(vsan.$vcenter.$datacentre.$cluster.esx.$hostname.vsan.$layer.stats.readBytes), 1), 'reads')",
              "textEditor": false
            },
            {
              "target": "alias(scaleToSeconds(derivative(vsan.$vcenter.$datacentre.$cluster.esx.$hostname.vsan.$layer.stats.writeBytes), 1), 'writes')",
              "textEditor": false
            },
            {
              "target": "alias(scaleToSeconds(derivative(vsan.$vcenter.$datacentre.$cluster.esx.$hostname.vsan.$layer.stats.recoveryWriteBytes), 1), 'recoveryWrites')",
              "textEditor": false
            },
            {
              "target": "alias(scaleToSeconds(derivative(removeBelowValue(vsan.$vcenter.$datacentre.$cluster.esx.$hostname.vsan.$layer.stats.resyncReadBytes, 0)), 1), 'resyncReadBytes')",
              "textEditor": false
            }
          ],
          "timeFrom": null,
          "timeShift": null,
          "title": "Bandwidth",
          "tooltip": {
            "shared": true,
            "sort": 0,
            "value_type": "cumulative"
          },
          "transparent": false,
          "type": "graph",
          "x-axis": true,
          "y-axis": true,
          "y_formats": [
            "Bps",
            "Bps"
          ]
        },
        {
          "aliasColors": {
            "readCong": "#CCA300",
            "recoveryWriteCong": "#890F02",
            "writeCong": "#C15C17"
          },
          "bars": false,
          "datasource": null,
          "editable": true,
          "error": false,
          "fill": 1,
          "grid": {
            "leftLogBase": 1,
            "leftMax": null,
            "leftMin": 0,
            "rightLogBase": 1,
            "rightMax": null,
            "rightMin": null,
            "threshold1": 15,
            "threshold1Color": "rgba(216, 200, 27, 0.15)",
            "threshold2": 20,
            "threshold2Color": "rgba(234, 112, 112, 0.14)"
          },
          "id": 13,
          "legend": {
            "avg": false,
            "current": false,
            "max": false,
            "min": false,
            "show": false,
            "total": false,
            "values": false
          },
          "lines": true,
          "linewidth": 2,
          "links": [],
          "nullPointMode": "null",
          "percentage": false,
          "pointradius": 5,
          "points": false,
          "renderer": "flot",
          "scopedVars": {
            "hostname": {
              "text": "ESX",
              "value": "",
              "selected": false
            }
          },
          "seriesOverrides": [],
          "span": 2,
          "stack": false,
          "steppedLine": false,
          "targets": [
            {
              "hide": true,
              "target": "derivative(vsan.$vcenter.$datacentre.$cluster.esx.$hostname.vsan.$layer.stats.readCount)",
              "textEditor": false
            },
            {
              "hide": true,
              "target": "derivative(vsan.$vcenter.$datacentre.$cluster.esx.$hostname.vsan.$layer.stats.writeCount)",
              "textEditor": false
            },
            {
              "hide": true,
              "target": "derivative(removeBelowValue(vsan.$vcenter.$datacentre.$cluster.esx.$hostname.vsan.$layer.stats.resyncReadCount, 0))",
              "textEditor": false
            },
            {
              "hide": false,
              "target": "alias(divideSeries(derivative(vsan.$vcenter.$datacentre.$cluster.esx.$hostname.vsan.$layer.stats.readCongestionSum), #A), 'readCong')",
              "textEditor": false
            },
            {
              "hide": false,
              "target": "alias(divideSeries(derivative(vsan.$vcenter.$datacentre.$cluster.esx.$hostname.vsan.$layer.stats.writeCongestionSum), #B), 'writeCong')",
              "textEditor": false
            },
            {
              "hide": false,
              "target": "alias(divideSeries(derivative(vsan.$vcenter.$datacentre.$cluster.esx.$hostname.vsan.$layer.stats.recoveryWriteCongestionSum), #B), 'recoveryWriteCong')",
              "textEditor": false
            },
            {
              "hide": false,
              "target": "alias(divideSeries(derivative(removeBelowValue(vsan.$vcenter.$datacentre.$cluster.esx.$hostname.vsan.$layer.stats.resyncReadCongestionSum, 0)), #C), 'resyncReadCong')",
              "textEditor": false
            }
          ],
          "timeFrom": null,
          "timeShift": null,
          "title": "Congestion",
          "tooltip": {
            "shared": true,
            "sort": 0,
            "value_type": "cumulative"
          },
          "transparent": false,
          "type": "graph",
          "x-axis": true,
          "y-axis": true,
          "y_formats": [
            "short",
            "short"
          ]
        },
        {
          "aliasColors": {
            "OIO": "#967302"
          },
          "bars": false,
          "datasource": null,
          "editable": true,
          "error": false,
          "fill": 1,
          "grid": {
            "leftLogBase": 1,
            "leftMax": null,
            "leftMin": 0,
            "rightLogBase": 1,
            "rightMax": null,
            "rightMin": null,
            "threshold1": null,
            "threshold1Color": "rgba(216, 200, 27, 0.27)",
            "threshold2": null,
            "threshold2Color": "rgba(234, 112, 112, 0.22)"
          },
          "id": 9,
          "legend": {
            "avg": false,
            "current": false,
            "max": false,
            "min": false,
            "show": false,
            "total": false,
            "values": false
          },
          "lines": true,
          "linewidth": 2,
          "links": [],
          "nullPointMode": "null",
          "percentage": false,
          "pointradius": 5,
          "points": false,
          "renderer": "flot",
          "scopedVars": {
            "hostname": {
              "text": "ESX",
              "value": "",
              "selected": false
            }
          },
          "seriesOverrides": [],
          "span": 2,
          "stack": false,
          "steppedLine": false,
          "targets": [
            {
              "hide": true,
              "target": "derivative(vsan.$vcenter.$datacentre.$cluster.esx.$hostname.vsan.$layer.stats.ioCount)",
              "textEditor": false
            },
            {
              "target": "alias(divideSeries(derivative(vsan.$vcenter.$datacentre.$cluster.esx.$hostname.vsan.$layer.stats.numOIOSum), #A), 'OIO')",
              "textEditor": false
            }
          ],
          "timeFrom": null,
          "timeShift": null,
          "title": "Outstanding IO",
          "tooltip": {
            "shared": true,
            "sort": 0,
            "value_type": "cumulative"
          },
          "transparent": false,
          "type": "graph",
          "x-axis": true,
          "y-axis": true,
          "y_formats": [
            "short",
            "short"
          ]
        },
        {
          "aliasColors": {
            "ClientCacheRate": "#EA6460",
            "readCacheRate": "#BA43A9"
          },
          "bars": false,
          "datasource": null,
          "editable": true,
          "error": false,
          "fill": 1,
          "grid": {
            "leftLogBase": 1,
            "leftMax": 100,
            "leftMin": 0,
            "rightLogBase": 1,
            "rightMax": null,
            "rightMin": 0,
            "threshold1": null,
            "threshold1Color": "rgba(216, 200, 27, 0.27)",
            "threshold2": null,
            "threshold2Color": "rgba(234, 112, 112, 0.22)"
          },
          "id": 28,
          "legend": {
            "avg": false,
            "current": false,
            "max": false,
            "min": false,
            "show": false,
            "total": false,
            "values": false
          },
          "lines": true,
          "linewidth": 2,
          "links": [],
          "nullPointMode": "null",
          "percentage": false,
          "pointradius": 5,
          "points": false,
          "renderer": "flot",
          "scopedVars": {
            "hostname": {
              "text": "ESX",
              "value": "",
              "selected": false
            }
          },
          "seriesOverrides": [],
          "span": 2,
          "stack": false,
          "steppedLine": false,
          "targets": [
            {
              "hide": true,
              "target": "derivative(vsan.$vcenter.$datacentre.$cluster.esx.$hostname.vsan.$layer.stats.readCount)",
              "textEditor": false
            },
            {
              "hide": false,
              "target": "alias(asPercent(derivative(vsan.$vcenter.$datacentre.$cluster.esx.$hostname.vsan.$layer.stats.readCachedCount), #A), 'readCacheRate')",
              "textEditor": false
            },
            {
              "hide": true,
              "target": "derivative(removeBelowValue(vsan.$vcenter.$datacentre.$cluster.esx.$hostname.vsan.client.cachestats.lookups, 0))",
              "textEditor": false
            },
            {
              "hide": false,
              "target": "alias(asPercent(derivative(removeBelowValue(vsan.$vcenter.$datacentre.$cluster.esx.$hostname.vsan.client.cachestats.hits, 0)), #C), 'ClientCacheRate')",
              "textEditor": false
            }
          ],
          "timeFrom": null,
          "timeShift": null,
          "title": "Caches Hit Rate",
          "tooltip": {
            "shared": true,
            "sort": 0,
            "value_type": "cumulative"
          },
          "transparent": false,
          "type": "graph",
          "x-axis": true,
          "y-axis": true,
          "y_formats": [
            "percent",
            "none"
          ]
        }
      ],
      "repeat": "hostname",
      "scopedVars": {
        "hostname": {
          "text": "ESX",
          "value": "",
          "selected": false
        }
      },
      "showTitle": true,
      "title": "$hostname"
    }
  ],
  "nav": [
    {
      "collapse": false,
      "enable": true,
      "notice": false,
      "now": true,
      "refresh_intervals": [
        "1m",
        "5m",
        "15m",
        "30m",
        "1h",
        "2h",
        "1d"
      ],
      "status": "Stable",
      "time_options": [
        "30min",
        "1h",
        "2h",
        "3h",
        "6h",
        "12h",
        "24h",
        "2d",
        "3d",
        "7d",
        "15d",
        "30d"
      ],
      "type": "timepicker"
    }
  ],
  "time": {
    "from": "now-1h",
    "to": "now"
  },
  "templating": {
    "list": [
      {
        "allFormat": "wildcard",
        "allValue": "*",
        "current": {
          "text": "All",
          "value": "*"
        },
        "datasource": null,
        "includeAll": true,
        "multi": true,
        "multiFormat": "glob",
        "name": "vcenter",
        "options": [
          {
            "text": "All",
            "value": "*",
            "selected": true
          }
        ],
        "query": "vsan.*",
        "refresh": true,
        "refresh_on_load": false,
        "regex": "",
        "type": "query"
      },
      {
        "allFormat": "wildcard",
        "allValue": "*",
        "current": {
          "text": "All",
          "value": "*"
        },
        "datasource": null,
        "includeAll": true,
        "multi": true,
        "multiFormat": "glob",
        "name": "datacentre",
        "options": [
          {
            "text": "All",
            "value": "*",
            "selected": true
          }
        ],
        "query": "vsan.$vcenter.*",
        "refresh": true,
        "refresh_on_load": false,
        "regex": "",
        "type": "query"
      },
      {
        "allFormat": "glob",
        "current": {
          "text": "None",
          "value": "",
          "isNone": true
        },
        "datasource": null,
        "includeAll": false,
        "multi": false,
        "multiFormat": "glob",
        "name": "cluster",
        "options": [
          {
            "text": "None",
            "value": "",
            "isNone": true,
            "selected": true
          }
        ],
        "query": "vsan.$vcenter.$datacentre.*",
        "refresh": true,
        "refresh_on_load": false,
        "regex": "",
        "type": "query"
      },
      {
        "allFormat": "wildcard",
        "allValue": "*",
        "current": {
          "text": "All",
          "value": "*"
        },
        "datasource": null,
        "hideLabel": false,
        "includeAll": true,
        "label": "esx",
        "multi": true,
        "multiFormat": "glob",
        "name": "hostname",
        "options": [
          {
            "text": "All",
            "value": "*",
            "selected": true
          }
        ],
        "query": "vsan.$vcenter.$datacentre.$cluster.esx.*",
        "refresh": true,
        "refresh_on_load": false,
        "regex": "",
        "type": "query",
        "useTags": false
      },
      {
        "allFormat": "glob",
        "current": {
          "tags": [],
          "text": "client",
          "value": "client"
        },
        "datasource": null,
        "includeAll": false,
        "multi": false,
        "multiFormat": "glob",
        "name": "layer",
        "options": [
          {
            "selected": true,
            "text": "client",
            "value": "client"
          },
          {
            "selected": false,
            "text": "disks",
            "value": "compmgr"
          },
          {
            "selected": false,
            "text": "owner",
            "value": "owner"
          }
        ],
        "query": "client,compmgr,owner",
        "refresh_on_load": false,
        "type": "custom"
      }
    ]
  },
  "annotations": {
    "list": []
  },
  "refresh": "1m",
  "schemaVersion": 6,
  "version": 12,
  "links": []
}